Metadata-Version: 2.1
Name: odoo-addon-purchase_location_by_line
Version: 18.0.1.0.1
Requires-Python: >=3.10
Requires-Dist: odoo-addon-purchase_delivery_split_date==18.0.*
Requires-Dist: odoo==18.0.*
Summary: Allows to define a specific destination location on each PO line
Home-page: https://github.com/OCA/purchase-workflow
License: AGPL-3
Author: ForgeFlow, Odoo Community Association (OCA)
Author-email: support@odoo-community.org
Classifier: Programming Language :: Python
Classifier: Framework :: Odoo
Classifier: Framework :: Odoo :: 18.0
Classifier: License :: OSI Approved :: GNU Affero General Public License v3
